st_span_annotation/__init__.py
st_span_annotation/frontend/build/asset-manifest.json
st_span_annotation/frontend/build/bootstrap.min.css
st_span_annotation/frontend/build/index.html
st_span_annotation/frontend/build/static/js/main.9fcefe0a.js
st_span_annotation/frontend/build/static/js/main.9fcefe0a.js.LICENSE.txt
st_span_annotation/frontend/build/static/js/main.9fcefe0a.js.map
st_span_annotation-0.0.8.dist-info/LICENSE
st_span_annotation-0.0.8.dist-info/METADATA
st_span_annotation-0.0.8.dist-info/WHEEL
st_span_annotation-0.0.8.dist-info/top_level.txt
st_span_annotation-0.0.8.dist-info/RECORD
